srsrpy/__init__.py
srsrpy/srsrpy.py
srsrpy/contrib/__init__.py
srsrpy/contrib/flask.py
srsrpy-1.1.0.dist-info/METADATA
srsrpy-1.1.0.dist-info/WHEEL
srsrpy-1.1.0.dist-info/licenses/LICENSE
srsrpy-1.1.0.dist-info/RECORD
