Metadata-Version: 2.4
Name: srsrpy
Version: 1.1.0
Summary: Really Simple Service Registry - Python Client
Project-URL: Documentation, https://github.com/ifIMust/srsrpy#readme
Project-URL: Source, https://github.com/ifIMust/srsrpy
Author-email: ifIMust <42818748+ifIMust@users.noreply.github.com>
License-Expression: MIT
License-File: LICENSE
Classifier: Development Status :: 4 - Beta
Classifier: Programming Language :: Python
Classifier: Programming Language :: Python :: 3.8
Classifier: Programming Language :: Python :: 3.9
Classifier: Programming Language :: Python :: 3.10
Classifier: Programming Language :: Python :: 3.11
Classifier: Programming Language :: Python :: 3.12
Classifier: Programming Language :: Python :: Implementation :: CPython
Classifier: Programming Language :: Python :: Implementation :: PyPy
Requires-Python: >=3.8
Requires-Dist: requests==2.32.4
Provides-Extra: flask
Requires-Dist: flask>=2.0.0; extra == 'flask'
